{
  "version": 3,
  "middleware": {
    "/": {
      "files": [
        "server/edge-runtime-webpack.js",
        "server/src/middleware.js"
      ],
      "name": "src/middleware",
      "page": "/",
      "matchers": [
        {
          "regexp": "^(?:\\/(_next\\/data\\/[^/]{1,}))?(?:\\/((?!api|onboarding|_next\\/static|_next\\/image|favicon.ico|robots.txt|sitemap.xml|assets|fonts|images|.*\\.(?:png|jpg|jpeg|gif|svg|ico|webp|mp4|webm|css|js)).*))(\\.json)?[\\/#\\?]?$",
          "originalSource": "/((?!api|onboarding|_next/static|_next/image|favicon.ico|robots.txt|sitemap.xml|assets|fonts|images|.*\\.(?:png|jpg|jpeg|gif|svg|ico|webp|mp4|webm|css|js)).*)"
        }
      ],
      "wasm": [],
      "assets": [],
      "env": {
        "__NEXT_BUILD_ID": "d9AUAXXrIvINhE_ThhNFC",
        "NEXT_SERVER_ACTIONS_ENCRYPTION_KEY": "+O3feajbbAPqIf0iOmGia3cyCYBQLUjZNn9FJVHbZXI=",
        "__NEXT_PREVIEW_MODE_ID": "49982b09ac7e06ebe78e244d21f0d7d8",
        "__NEXT_PREVIEW_MODE_ENCRYPTION_KEY": "cbd974b921340b2f5e0f6a597c8c71e8e248c35127f3d9059b1f67bdc8b7402a",
        "__NEXT_PREVIEW_MODE_SIGNING_KEY": "dd2bddb210ee249145ee7a41e8b20a15548764e4ff6462051553bfb7c1bacd8d"
      }
    }
  },
  "functions": {},
  "sortedMiddleware": [
    "/"
  ]
}